obsidian_sdk/__init__.py
obsidian_sdk/log.py
obsidian_sdk/mcp.py
obsidian_sdk/server.py
obsidian_sdk/utils.py
obsidian_sdk/canvas/__init__.py
obsidian_sdk/canvas/canvas.py
obsidian_sdk/canvas/kanbanz.py
obsidian_sdk/canvas/obsidian_parser.py
obsidian_sdk-0.1.4.dist-info/METADATA
obsidian_sdk-0.1.4.dist-info/WHEEL
obsidian_sdk-0.1.4.dist-info/top_level.txt
obsidian_sdk-0.1.4.dist-info/RECORD
